<?xml version="1.0" encoding="utf-8" ?>
<thread  xmlns:xsi="http://www.w3.org/2001/XMLSchema-instance" xsi:noNamespaceSchemaLocation="http://forum.mods.de/bb/forum.xsd" current-user-id="0" id="213115"><title><![CDATA[Krieg der Töpfe CIII - Herbstgemüse]]></title><subtitle><![CDATA[Kürbis, Kohl, Kastanien?]]></subtitle><number-of-replies value='31' /><number-of-hits value='9297' /><number-of-pages value='2' /><flags><is-closed value="0" /><is-sticky value="1" /><is-important value="0" /><is-announcement value="0" /><is-global value="0" /></flags><in-board id="14" /><firstpost><post><user id="1328618"><![CDATA[Dagrachon]]></user><date timestamp="1413023636">11.10.2014 12:33:56</date><icon id="2" /><in-thread id="213115" /><in-board id="14" /></post></firstpost><posts page="1" offset="0" count="30"><post id="1245618462"><user id="1328618" group-id="3"><![CDATA[Dagrachon]]></user><date timestamp="1413023636">11.10.2014 12:33:56</date><message>
      <edited count="1"><lastedit>
        <user id="5652"><![CDATA[Atomsk]]></user>
        <date timestamp="1413023795">11.10.2014 12:36:35</date>
      </lastedit></edited>
      <content><![CDATA[[img]http://img.pichoster.eu/6ac4fc501333046276.jpg[/img]

Ihr habt vier Wochen Zeit, das im Thread für die aktuelle Runde vorgegebene Gericht zu kochen, und den Schaffensvorgang sowie das Ergebnis zu posten.
Die Bezeichnung des Gerichts ist mit voller Absicht relativ allgemein gehalten, so dass jeder Forenkoch "seine" Variante zubereiten kann.
Für die Gestaltung des Wettbewerbsbeitrages - eures Posts - gibt es keinerlei Regeln, mit einer Ausnahme: Die gesamte Präsentation muss in einem Post untergebracht werden.

Den Sieger bestimmen die User dieses Forums über die Abstimmungs-Funktion im Forum. Natürlich mag das nicht wirklich repräsentativ und manipulationssicher sein, aber da das hier eine reine Spaßveranstaltung ist, interessiert das letzten Endes auch keinen Menschen.
Ob ihr mit außergewöhnlichem Essen, einer detaillierten Beschreibung oder tollen Bildern punktet, entscheiden also die User eures Forums; Ortskenntnis könnte daher hilfreich sein.

Dem Sieger winkt neben ewigem Ruhm im Forum die Ehre, das nächste Gericht vorzuschlagen.

Das Thema, welches bis zum [mod]09.11.2014 um 23.59 Uhr[/mod] in ein leckeres Gericht umzuwandeln und vorzuführen ist, lautet:

[mod]Herbstgemüse - Kürbis, Kohl, Kastanien?[/mod]

Glückwunsch an SpassCola zum Gewinn des letzten KdTs und danke für das neue Thema!


Viel Spaß beim Kochen :)]]></content>
      <title><![CDATA[Kürbis, Kohl, Kastanien?]]></title>
    </message><avatar id="60924"><![CDATA[./avatare/upload/U1328618--bender_dagrachon_dota_final_125px.png]]></avatar><icon id="2"><![CDATA[./img/icons/thumbsup.gif]]></icon><in-thread id="213115"><![CDATA[Krieg der Töpfe CIII - Herbstgemüse]]></in-thread><in-board id="14" /></post><post id="1245618865"><user id="1296761" group-id="3"><![CDATA[dictyosom]]></user><date timestamp="1413039563">11.10.2014 16:59:23</date><message>
      <edited count="0"></edited>
      <content><![CDATA[Schönes Thema, ich hoffe da kommt viel :)]]></content>
      <title></title>
    </message><avatar id="60920"><![CDATA[./avatare/upload/U1296761--ceras_s2okjfs.png]]></avatar><in-thread id="213115"><![CDATA[Krieg der Töpfe CIII - Herbstgemüse]]></in-thread><in-board id="14" /></post><post id="1245618983"><user id="1246933" group-id="3"><![CDATA[The_gonzo]]></user><date timestamp="1413044029">11.10.2014 18:13:49</date><message>
      <edited count="0"></edited>
      <content><![CDATA[Kürbis und Kastaniensuppe mit ganzen Früchten.]]></content>
      <title></title>
    </message><avatar id="60515"><![CDATA[./avatare/upload/U1246933--3-klein.gif]]></avatar><icon id="2"><![CDATA[./img/icons/thumbsup.gif]]></icon><in-thread id="213115"><![CDATA[Krieg der Töpfe CIII - Herbstgemüse]]></in-thread><in-board id="14" /></post><post id="1245621320"><user id="1195872" group-id="3"><![CDATA[nekojin]]></user><date timestamp="1413213120">13.10.2014 17:12:00</date><message>
      <edited count="0"></edited>
      <content><![CDATA[Yummy <3]]></content>
      <title></title>
    </message><avatar id="60869"><![CDATA[./avatare/upload/U1195872--orcs_must_die_kl.png]]></avatar><in-thread id="213115"><![CDATA[Krieg der Töpfe CIII - Herbstgemüse]]></in-thread><in-board id="14" /></post><post id="1245621773"><user id="60666" group-id="3"><![CDATA[Futura]]></user><date timestamp="1413229825">13.10.2014 21:50:25</date><message>
      <edited count="0"></edited>
      <content><![CDATA[Grünkohl mit Pinkel \o/]]></content>
      <title></title>
    </message><avatar id="59474"><![CDATA[./avatare/Futura.gif]]></avatar><in-thread id="213115"><![CDATA[Krieg der Töpfe CIII - Herbstgemüse]]></in-thread><in-board id="14" /></post><post id="1245621784"><user id="35563" group-id="3"><![CDATA[SpassCola]]></user><date timestamp="1413230349">13.10.2014 21:59:09</date><message>
      <edited count="1"><lastedit>
        <user id="35563"><![CDATA[SpassCola]]></user>
        <date timestamp="1413231070">13.10.2014 22:11:10</date>
      </lastedit></edited>
      <content><![CDATA[Ich alter Wizard kombiniere einfach Kürbis mit Pizza!

e: Mühsam den Quote zusammengeschustert

[quote=213091,1245618121,"Pikkoenig"]
[b]Kürbispizza?[/b]
[/quote]]]></content>
      <title></title>
    </message><avatar id="59217"><![CDATA[./avatare/arctic.gif]]></avatar><icon id="2"><![CDATA[./img/icons/thumbsup.gif]]></icon><in-thread id="213115"><![CDATA[Krieg der Töpfe CIII - Herbstgemüse]]></in-thread><in-board id="14" /></post><post id="1245621985"><user id="70323" group-id="3"><![CDATA[DarthChris]]></user><date timestamp="1413236788">13.10.2014 23:46:28</date><message>
      <edited count="0"></edited>
      <content><![CDATA[[quote=213115,1245621773,"Futura"][b]
Grünkohl mit Pinkel \o/
[/b][/quote]

Ich hätte davon gerne mal ein einfaches und möglichst schnelles Rezept. Wer das hinbekommt hat meine Stimme.]]></content>
      <title></title>
    </message><avatar id="59225"><![CDATA[./avatare/guerilla.gif]]></avatar><in-thread id="213115"><![CDATA[Krieg der Töpfe CIII - Herbstgemüse]]></in-thread><in-board id="14" /></post><post id="1245622531"><user id="1332229" group-id="3"><![CDATA[Admiral Bohm]]></user><date timestamp="1413287073">14.10.2014 13:44:33</date><message>
      <edited count="0"></edited>
      <content><![CDATA[[quote=213115,1245621784,"SpassCola"][b]
Ich alter Wizard kombiniere einfach Kürbis mit Pizza!

e: Mühsam den Quote zusammengeschustert

[quote=213091,1245618121,"Pikkoenig"]
[b]Kürbispizza?[/b]
[/quote]
[/b][/quote]

Vermutlich komme ich nicht dazu, aber das war meine Idee. :mad:]]></content>
      <title></title>
    </message><avatar id="60479"><![CDATA[./avatare/tf2_spy.png]]></avatar><in-thread id="213115"><![CDATA[Krieg der Töpfe CIII - Herbstgemüse]]></in-thread><in-board id="14" /></post><post id="1245622541"><user id="62612" group-id="3"><![CDATA[Mobius]]></user><date timestamp="1413287695">14.10.2014 13:54:55</date><message>
      <edited count="0"></edited>
      <content><![CDATA[[quote=213115,1245621773,"Futura"][b]
Grünkohl mit Pinkel \o/
[/b][/quote]

Das ist Winteressen, Grünkohl erntet man im eigenen Garten erst nach dem Frost und erntet den Winter über weiter. Natürlich lässt sich das jetzt schon ernten, aber es schmeckt im Dezember nach einer Winterwanderung am besten. Lecker Kassler, Pinkel, Kohlwurst und scharf geräucherte Mettendchen dabei. <3]]></content>
      <title></title>
    </message><avatar id="59484"><![CDATA[./avatare/mob8.gif]]></avatar><in-thread id="213115"><![CDATA[Krieg der Töpfe CIII - Herbstgemüse]]></in-thread><in-board id="14" /></post><post id="1245624855"><user id="35563" group-id="3"><![CDATA[SpassCola]]></user><date timestamp="1413391057">15.10.2014 18:37:37</date><message>
      <edited count="1"><lastedit>
        <user id="35563"><![CDATA[SpassCola]]></user>
        <date timestamp="1413406437">15.10.2014 22:53:57</date>
      </lastedit></edited>
      <content><![CDATA[[b]Zutatenliste[/b]

[list][b]Teig[/b]
[*]175g Mehl
[*]80g Magerquark
[*]1TL Backpulver
[*]1 Ei
[*]3EL Olivenöl
[*]Salz
[/list]

[list][b]Belag[/b]
[*]400g Kürbis
[*]2 rote Zwiebeln
[*]Olivenöl
[*]Creme Fraiche
[*]Feta
[*]2TL Honig
[*]Chili
[*]1 Paprika
[*]3 Frühlingszwiebeln
[*]n.B. Salz &amp; Pfeffer
[/list]

[img]http://www.macrovis-web.de/wp-content/uploads/2014/10/2014-10-15-17.02.31.jpg[/img]

Backofen auf 250° vorheizen.

Aus dem Magerquark, Mehl, Ei, Backpulver, Olivenöl und ein wenig Salz den Teig kneten und auf Backpapier dünn ausrollen.

Den Kürbis je nach Form schälen, entkernen und in feine Scheiben schneiden. Scharf in einer Pfanne anbraten und leicht salzen.

[img]http://www.macrovis-web.de/wp-content/uploads/2014/10/2014-10-15-17.25.17.jpg[/img]

In einer Schüssel auskühlen lassen. In die Schüssel kommen dann fein geschnittene Frühlingszwiebeln, Paprika, Chili, Honig, Olivenöl, geachtelte und geschälte Zwiebeln, etwas salzen &amp; pfeffern.
Alles gut vermischen und kurz ziehen lassen.

[img]http://www.macrovis-web.de/wp-content/uploads/2014/10/2014-10-15-17.31.39.jpg[/img]

In der Zwischenzeit die Creme Fraiche dünn auf dem Teig verteilen, geht am besten mit einem Löffel.
Dann die Zutaten aus der Schüssel auf dem Teig verteilen und klein zerteilten Feta darüber streuen.

[img]http://www.macrovis-web.de/wp-content/uploads/2014/10/2014-10-15-17.38.39.jpg[/img]

Eventuell nochmal nachpfeffern und ein paar Spritzer Olivenöl darüber verteilen.
Das Ganze kommt nun bei den 250° auf ein Backblech und bleibt dann 15min im Ofen.

[img]http://www.macrovis-web.de/wp-content/uploads/2014/10/2014-10-15-17.57.18.jpg[/img]

[img]http://www.macrovis-web.de/wp-content/uploads/2014/10/2014-10-15-17.58.29.jpg[/img]]]></content>
      <title><![CDATA[Kürbispizza]]></title>
    </message><avatar id="59217"><![CDATA[./avatare/arctic.gif]]></avatar><in-thread id="213115"><![CDATA[Krieg der Töpfe CIII - Herbstgemüse]]></in-thread><in-board id="14" /></post><post id="1245625240"><user id="57196" group-id="3"><![CDATA[Filmriss]]></user><date timestamp="1413402107">15.10.2014 21:41:47</date><message>
      <edited count="0"></edited>
      <content><![CDATA[Die Farben <3 <3]]></content>
      <title></title>
    </message><avatar id="59219"><![CDATA[./avatare/leet.gif]]></avatar><icon id="54"><![CDATA[./img/icons/pfeil.gif]]></icon><in-thread id="213115"><![CDATA[Krieg der Töpfe CIII - Herbstgemüse]]></in-thread><in-board id="14" /></post><post id="1245625749"><user id="59304" group-id="3"><![CDATA[Spriggan]]></user><date timestamp="1413447117">16.10.2014 10:11:57</date><message>
      <edited count="0"></edited>
      <content><![CDATA[Richtig geil! Da fehlt nur noch ein bisschen Apfel, dann wäre es perfekt (mache ich immer noch gern mit drauf, passt wunderbar).]]></content>
      <title></title>
    </message><avatar id="59217"><![CDATA[./avatare/arctic.gif]]></avatar><in-thread id="213115"><![CDATA[Krieg der Töpfe CIII - Herbstgemüse]]></in-thread><in-board id="14" /></post><post id="1245626365"><user id="1180613" group-id="3"><![CDATA[gott.[shake]]]></user><date timestamp="1413474329">16.10.2014 17:45:29</date><message>
      <edited count="0"></edited>
      <content><![CDATA[Vielleicht ein bisschen viel Belag, sieht sonst aber geil aus!]]></content>
      <title></title>
    </message><avatar id="60475"><![CDATA[./avatare/upload/U1180613--gottshake.gif]]></avatar><in-thread id="213115"><![CDATA[Krieg der Töpfe CIII - Herbstgemüse]]></in-thread><in-board id="14" /></post><post id="1245628752"><user id="63365" group-id="3"><![CDATA[]Maestro[]]></user><date timestamp="1413623787">18.10.2014 11:16:27</date><message>
      <edited count="0"></edited>
      <content><![CDATA[[quote=213115,1245626365,"gott.[shake]"][b]
Vielleicht ein bisschen viel Belag, sieht sonst aber geil aus!
[/b][/quote]

Diese "blos nicht zuviel" Pizzabeleger werde ich nie verstehen. :D]]></content>
      <title></title>
    </message><avatar id="60917"><![CDATA[./avatare/upload/U63365--scratchbendersmall.png]]></avatar><in-thread id="213115"><![CDATA[Krieg der Töpfe CIII - Herbstgemüse]]></in-thread><in-board id="14" /></post><post id="1245629092"><user id="1246933" group-id="3"><![CDATA[The_gonzo]]></user><date timestamp="1413638332">18.10.2014 15:18:52</date><message>
      <edited count="0"></edited>
      <content><![CDATA[[quote=213115,1245626365,"gott.[shake]"][b]
Vielleicht ein bisschen viel Belag, sieht sonst aber geil aus!
[/b][/quote]

Zu viel gibts nicht!

[IMG]http://i.imgur.com/1rFzhG7l.jpg[/img]]]></content>
      <title></title>
    </message><avatar id="60515"><![CDATA[./avatare/upload/U1246933--3-klein.gif]]></avatar><in-thread id="213115"><![CDATA[Krieg der Töpfe CIII - Herbstgemüse]]></in-thread><in-board id="14" /></post><post id="1245629093"><user id="1180613" group-id="3"><![CDATA[gott.[shake]]]></user><date timestamp="1413638392">18.10.2014 15:19:52</date><message>
      <edited count="0"></edited>
      <content><![CDATA[[quote=213115,1245628752,"]Maestro["][b]
[quote=213115,1245626365,"gott.[shake]"][b]
Vielleicht ein bisschen viel Belag, sieht sonst aber geil aus!
[/b][/quote]

Diese "blos nicht zuviel" Pizzabeleger werde ich nie verstehen. :D
[/b][/quote]

Ich wills ja auch noch vernünftig essen können, d.h. ohne Messer und Gabel!]]></content>
      <title></title>
    </message><avatar id="60475"><![CDATA[./avatare/upload/U1180613--gottshake.gif]]></avatar><in-thread id="213115"><![CDATA[Krieg der Töpfe CIII - Herbstgemüse]]></in-thread><in-board id="14" /></post><post id="1245629790"><user id="63365" group-id="3"><![CDATA[]Maestro[]]></user><date timestamp="1413663491">18.10.2014 22:18:11</date><message>
      <edited count="0"></edited>
      <content><![CDATA[Dann nimm beide Hände!]]></content>
      <title></title>
    </message><avatar id="60917"><![CDATA[./avatare/upload/U63365--scratchbendersmall.png]]></avatar><in-thread id="213115"><![CDATA[Krieg der Töpfe CIII - Herbstgemüse]]></in-thread><in-board id="14" /></post><post id="1245630130"><user id="74373" group-id="3"><![CDATA[Oli]]></user><date timestamp="1413709979">19.10.2014 11:12:59</date><message>
      <edited count="0"></edited>
      <content><![CDATA[Ich arbeite dieses Jahr an nem kleinen Kochbuch mit meiner Freundin, deshalb habe ich auch mal ein Rezept parat. Mein Debüt hier im Thread. :)



[b]Kürbisflammkuchen[/b]

250g Mehl
1/2 Würfel frische oder 1/2 Pck. Backhefe
1/2 TL Zucker
5 EL Olivenöl
Salz
Pfeffer
Thymian
600g Hokkaidokürbis
200g Crème Fraiche
125g kräftiger Blauschimmelkäse
2 EL Kürbiskerne oder Walnüsse o.ä.

[list=1]
[*]Mehl, Hefe, 1/2 TL Salz, 2 EL Olivenöl, 100 ml lauwarmes Wasser mischen und zu einem Teig kneten. 45 Minuten gehen lassen.
[*]Kürbis Innenleben entfernen und in Spalten schneiden (siehe Bild). Spalten im restlichen Olivenöl 2-3 Minuten von beiden Seiten anbraten und mit Pfeffer/Salz würzen
[*]Teig ausrollen, mit Crème Fraiche bestreichen und mit den Kürbisspalten belegen. Den Blauschimmelkäse klein schneiden und auf dem Teig verteilen. Thymian druff und am Ende noch die Walnüsse / Kürbiskerne.
[*]Das ganze im 220grad vorgeheiztem Backofen 15 Minuten lang backen.
[/list]

Die Zutaten
[url=http://abload.de/image.php?img=dscf8475ggudm.jpg][img]http://abload.de/thumb/dscf8475ggudm.jpg[/img][/url]

Kürbis anbraten
[url=http://abload.de/image.php?img=dscf8478copyzlukt.jpg][img]http://abload.de/thumb/dscf8478copyzlukt.jpg[/img][/url]

Alles auf den Teig
[url=http://abload.de/image.php?img=dscf8486copyaouew.jpg][img]http://abload.de/thumb/dscf8486copyaouew.jpg[/img][/url]

Nachher sieht's fast so aus wie vorher. :)
[url=http://abload.de/image.php?img=dscf8487copyp8uno.jpg][img]http://abload.de/thumb/dscf8487copyp8uno.jpg[/img][/url]]]></content>
      <title></title>
    </message><avatar id="60843"><![CDATA[./avatare/upload/U74373--paket1s.gif]]></avatar><in-thread id="213115"><![CDATA[Krieg der Töpfe CIII - Herbstgemüse]]></in-thread><in-board id="14" /></post><post id="1245630598"><user id="1296761" group-id="3"><![CDATA[dictyosom]]></user><date timestamp="1413733107">19.10.2014 17:38:27</date><message>
      <edited count="0"></edited>
      <content><![CDATA[Uh, die Kombination mit Blauschimmelkäse klingt gut!]]></content>
      <title></title>
    </message><avatar id="60920"><![CDATA[./avatare/upload/U1296761--ceras_s2okjfs.png]]></avatar><in-thread id="213115"><![CDATA[Krieg der Töpfe CIII - Herbstgemüse]]></in-thread><in-board id="14" /></post><post id="1245630645"><user id="35563" group-id="3"><![CDATA[SpassCola]]></user><date timestamp="1413735687">19.10.2014 18:21:27</date><message>
      <edited count="0"></edited>
      <content><![CDATA[Das klingt wirklich richtig lecker [img]http://forum.mods.de/bb/img/icons/thumbsup.gif[/img]

Ich hatte mal Lust auf einen kompletten Kürbis zu verarbeiten und zum ersten mal einen Hokkaidokürbis gekauft.

[b]Kürbissuppe mit Kokosmilch[/b]

[b]Zutatenliste[/b]
[list]
[*]1 Hokkaidokürbis
[*]2 Zwiebeln
[*]5cm Ingwer
[*]1 Apfel
[*]1 Liter Gemüsebrühe
[*]400ml Kokosmilch
[*]Chili
[*]Olivenöl
[*]n.B. Salz, Zucker/Honig
[/list]

[img]http://www.macrovis-web.de/wp-content/uploads/2014/10/2014-10-18-11.37.54.jpg[/img]

Zwiebeln grob hacken und scharf in einem Bräter mit Olivenöl vorbraten. Den Kürbis schälen, entkernen und gewürfelt zu den Zwiebeln geben.
Apfel vom Kern befreien, grob hacken und mit geschältem und zerkleinertem Ingwer mit anbraten.

[img]http://www.macrovis-web.de/wp-content/uploads/2014/10/2014-10-18-12.20.24.jpg[/img]

Mit Gemüsebrühe ablöschen und ca. 15min köcheln lassen bei mittlerer Hitze.
Mit einem Pürierstab alles zerkleinern und die Kokosmilch hinzugeben.

Jetzt mit Salz, Zucker/Honig und Chili abschmecken, fertig.

[img]http://www.macrovis-web.de/wp-content/uploads/2014/10/2014-10-19-11.09.35.jpg[/img]

Mit getrockneten Chilifäden und Olivenöl dekorieren.]]></content>
      <title></title>
    </message><avatar id="59217"><![CDATA[./avatare/arctic.gif]]></avatar><in-thread id="213115"><![CDATA[Krieg der Töpfe CIII - Herbstgemüse]]></in-thread><in-board id="14" /></post><post id="1245630703"><user id="1241980" group-id="3"><![CDATA[Chinakohl mit Reis]]></user><date timestamp="1413738389">19.10.2014 19:06:29</date><message>
      <edited count="0"></edited>
      <content><![CDATA[Mit Kokosmilch und Ingwer machen wir unsere Kürbissuppe auch immer.]]></content>
      <title></title>
    </message><avatar id="59217"><![CDATA[./avatare/arctic.gif]]></avatar><icon id="2"><![CDATA[./img/icons/thumbsup.gif]]></icon><in-thread id="213115"><![CDATA[Krieg der Töpfe CIII - Herbstgemüse]]></in-thread><in-board id="14" /></post><post id="1245630795"><user id="1296761" group-id="3"><![CDATA[dictyosom]]></user><date timestamp="1413741769">19.10.2014 20:02:49</date><message>
      <edited count="0"></edited>
      <content><![CDATA[Hokkaido muss man nicht schälen! :)]]></content>
      <title></title>
    </message><avatar id="60920"><![CDATA[./avatare/upload/U1296761--ceras_s2okjfs.png]]></avatar><in-thread id="213115"><![CDATA[Krieg der Töpfe CIII - Herbstgemüse]]></in-thread><in-board id="14" /></post><post id="1245632331"><user id="1246933" group-id="3"><![CDATA[The_gonzo]]></user><date timestamp="1413830248">20.10.2014 20:37:28</date><message>
      <edited count="0"></edited>
      <content><![CDATA[Kernöl! Ihr habt alle das Kernöl vergessen!]]></content>
      <title></title>
    </message><avatar id="60515"><![CDATA[./avatare/upload/U1246933--3-klein.gif]]></avatar><in-thread id="213115"><![CDATA[Krieg der Töpfe CIII - Herbstgemüse]]></in-thread><in-board id="14" /></post><post id="1245639490"><user id="21000" group-id="3"><![CDATA[Lucifer]]></user><date timestamp="1414240997">25.10.2014 14:43:17</date><message>
      <edited count="1"><lastedit>
        <user id="21000"><![CDATA[Lucifer]]></user>
        <date timestamp="1414241099">25.10.2014 14:44:59</date>
      </lastedit></edited>
      <content><![CDATA[[quote=213115,1245630645,"SpassCola"][b]
Das klingt wirklich richtig lecker [img]http://forum.mods.de/bb/img/icons/thumbsup.gif[/img]

Ich hatte mal Lust auf einen kompletten Kürbis zu verarbeiten und zum ersten mal einen Hokkaidokürbis gekauft.

[b]Kürbissuppe mit Kokosmilch[/b]

[b]Zutatenliste[/b]
[list]
[*]1 Hokkaidokürbis
[*]2 Zwiebeln
[*]5cm Ingwer
[*]1 Apfel
[*]1 Liter Gemüsebrühe
[*]400ml Kokosmilch
[*]Chili
[*]Olivenöl
[*]n.B. Salz, Zucker/Honig
[/list]

[url]http://www.macrovis-web.de/wp-content/uploads/2014/10/2014-10-18-11.37.54.jpg[/url]

Zwiebeln grob hacken und scharf in einem Bräter mit Olivenöl vorbraten. Den Kürbis schälen, entkernen und gewürfelt zu den Zwiebeln geben.
Apfel vom Kern befreien, grob hacken und mit geschältem und zerkleinertem Ingwer mit anbraten.

[url]http://www.macrovis-web.de/wp-content/uploads/2014/10/2014-10-18-12.20.24.jpg[/url]

Mit Gemüsebrühe ablöschen und ca. 15min köcheln lassen bei mittlerer Hitze.
Mit einem Pürierstab alles zerkleinern und die Kokosmilch hinzugeben.

Jetzt mit Salz, Zucker/Honig und Chili abschmecken, fertig.

[url]http://www.macrovis-web.de/wp-content/uploads/2014/10/2014-10-19-11.09.35.jpg[/url]

Mit getrockneten Chilifäden und Olivenöl dekorieren.
[/b][/quote]

Ich kenn das Grundrezept von Chefkoch, gibts morgen bei uns. Ist wirklich richtig lecker obwohl ich alles andere als Kürbisfan bin. Noch Apfel und Chili dazu klingt nach interessanter Kombination.]]></content>
      <title></title>
    </message><avatar id="59375"><![CDATA[./avatare/lucifer.gif]]></avatar><icon id="2"><![CDATA[./img/icons/thumbsup.gif]]></icon><in-thread id="213115"><![CDATA[Krieg der Töpfe CIII - Herbstgemüse]]></in-thread><in-board id="14" /></post><post id="1245641187"><user id="35563" group-id="3"><![CDATA[SpassCola]]></user><date timestamp="1414338814">26.10.2014 16:53:34</date><message>
      <edited count="1"><lastedit>
        <user id="35563"><![CDATA[SpassCola]]></user>
        <date timestamp="1414339043">26.10.2014 16:57:23</date>
      </lastedit></edited>
      <content><![CDATA[[i]Ey, ihr Fotzen, Herbstgerichte, Scheiße![/i]
[img]http://abload.de/img/bildschirmfoto2014-10hlqsf.jpg[/img]

[b]Kohlrouladen[/b]

[b]Zutatenliste[/b]
[list]
[*]1 Weißkohl
[*]80g Apfelringe
[*]1 Bund Petersilie
[*]1 El Fenchelsaat
[*]1 El Kümmel, ganz
[*]3 Zwiebeln
[*]500g Hackfleisch, gemischt
[*]2 Eier
[*]4 El Semmelbrösel
[*]200ml Schlagsahne
[*]200ml Apfelsaft
[*]300ml Gemüsebrühe
[*]2 Knoblauchzehen
[*]4 Lorbeerblätter
[*]Öl
[*]n.B. Salz &amp; Pfeffer
[/list]

[img]http://www.macrovis-web.de/wp-content/uploads/2014/10/2014-10-26-11.36.34.jpg[/img]

In einem großen Topf Wasser zum Kochen bringen. Aus dem Weißkohl den Strunk herausschneiden und mit einer Bratengabel oder Rouladenstäben hineinstechen.

[img]http://www.macrovis-web.de/wp-content/uploads/2014/10/2014-10-26-12.14.17.jpg[/img]

Den Weißkohl jetzt ins Wasser legen und ca. alle 2min lassen sich die äußeren Kohlblätter lösen.
Dann alle Blätter nochmal 5min im Wasser kochen lassen, abtropfen lassen und den dicken Stamm abschneiden.

[img]http://www.macrovis-web.de/wp-content/uploads/2014/10/2014-10-26-12.49.49.jpg[/img]

Apfelringe fein hacken und mit gehackter Petersilie in eine Schüssel geben.

Fenchelsaat und Kümmel in einer Pfanne ohne Öl erhitzen bis die angebräunt sind, dann im Mörser oder mit Mixstab fein zerkleinern, mit in die Schüssel geben.
In der Pfanne dann mit wenig Öl eine fein gehackte Zwiebel glasig braten und auch mit in die Schüssel geben.

In die Schüssel kommen jetzt noch Hack, die Eier, Semmelbrösel und 100ml Schlagsahne.
Ordentlich mit Salz und Pfeffer würzen und gut durchmischen.

[img]http://www.macrovis-web.de/wp-content/uploads/2014/10/2014-10-26-12.04.14.jpg[/img]

Jetzt jeweils 2 Kohlblätter überlappt übereinander legen, eventuell mit Nudelholz anpressen, und ein wenig Hackmasse darauf legen.
Die Kohlblattkanten übereinander legen und dann die Roulade rollen, auf der Naht hinlegen.

[img]http://www.macrovis-web.de/wp-content/uploads/2014/10/2014-10-26-12.52.55.jpg[/img]

Mit allen Kohlblätter weiter verfahren bis die Fleischmasse alle ist.

Nun die restlichen Zwiebeln und Knoblauch in Scheiben schneiden und mit etwas Öl in einem Bräter scharf anbraten.
Die Kohlrouladen hineinlegen, mit Apfelsaft und Gemüsebrühe ablöschen, Lorbeerblätter hinzugeben, nochmal nachwürzen und nochmal kurz aufkochen lassen.

[img]http://www.macrovis-web.de/wp-content/uploads/2014/10/2014-10-26-13.08.29.jpg[/img]

Dann bei 45min und 200° (keine Umluft) im Backofen garen lassen.
Zu guter letzt die Kohlrouladen und Lorbeerblätter aus dem Bräter nehmen, die restlichen 100ml Schlagsahne hinzugeben und mit einem Mixstab alles pürieren, ggf. nachwürzen.

[img]http://www.macrovis-web.de/wp-content/uploads/2014/10/2014-10-26-14.12.02.jpg[/img]

Dazu passen ganz gut Salzkartoffeln mit Petersilie.

[img]http://www.macrovis-web.de/wp-content/uploads/2014/10/2014-10-26-14.16.41.jpg[/img]

[img]http://www.macrovis-web.de/wp-content/uploads/2014/10/2014-10-26-14.17.23.jpg[/img]]]></content>
      <title></title>
    </message><avatar id="59217"><![CDATA[./avatare/arctic.gif]]></avatar><in-thread id="213115"><![CDATA[Krieg der Töpfe CIII - Herbstgemüse]]></in-thread><in-board id="14" /></post><post id="1245641273"><user id="117210" group-id="3"><![CDATA[clyderedcliff]]></user><date timestamp="1414342517">26.10.2014 17:55:17</date><message>
      <edited count="0"></edited>
      <content><![CDATA[[quote=213115,1245641187,"SpassCola"][b]
[i]Ey, ihr Fotzen, Herbstgerichte, Scheiße![/i]
[url]http://abload.de/img/bildschirmfoto2014-10hlqsf.jpg[/url]

[b]Kohlrouladen[/b]

[b]Zutatenliste[/b]
[list]
[*]1 Weißkohl
[*]80g Apfelringe
[*]1 Bund Petersilie
[*]1 El Fenchelsaat
[*]1 El Kümmel, ganz
[*]3 Zwiebeln
[*]500g Hackfleisch, gemischt
[*]2 Eier
[*]4 El Semmelbrösel
[*]200ml Schlagsahne
[*]200ml Apfelsaft
[*]300ml Gemüsebrühe
[*]2 Knoblauchzehen
[*]4 Lorbeerblätter
[*]Öl
[*]n.B. Salz &amp; Pfeffer
[/list]

[url]http://www.macrovis-web.de/wp-content/uploads/2014/10/2014-10-26-11.36.34.jpg[/url]

In einem großen Topf Wasser zum Kochen bringen. Aus dem Weißkohl den Strunk herausschneiden und mit einer Bratengabel oder Rouladenstäben hineinstechen.

[url]http://www.macrovis-web.de/wp-content/uploads/2014/10/2014-10-26-12.14.17.jpg[/url]

Den Weißkohl jetzt ins Wasser legen und ca. alle 2min lassen sich die äußeren Kohlblätter lösen.
Dann alle Blätter nochmal 5min im Wasser kochen lassen, abtropfen lassen und den dicken Stamm abschneiden.

[url]http://www.macrovis-web.de/wp-content/uploads/2014/10/2014-10-26-12.49.49.jpg[/url]

Apfelringe fein hacken und mit gehackter Petersilie in eine Schüssel geben.

Fenchelsaat und Kümmel in einer Pfanne ohne Öl erhitzen bis die angebräunt sind, dann im Mörser oder mit Mixstab fein zerkleinern, mit in die Schüssel geben.
In der Pfanne dann mit wenig Öl eine fein gehackte Zwiebel glasig braten und auch mit in die Schüssel geben.

In die Schüssel kommen jetzt noch Hack, die Eier, Semmelbrösel und 100ml Schlagsahne.
Ordentlich mit Salz und Pfeffer würzen und gut durchmischen.

[url]http://www.macrovis-web.de/wp-content/uploads/2014/10/2014-10-26-12.04.14.jpg[/url]

Jetzt jeweils 2 Kohlblätter überlappt übereinander legen, eventuell mit Nudelholz anpressen, und ein wenig Hackmasse darauf legen.
Die Kohlblattkanten übereinander legen und dann die Roulade rollen, auf der Naht hinlegen.

[url]http://www.macrovis-web.de/wp-content/uploads/2014/10/2014-10-26-12.52.55.jpg[/url]

Mit allen Kohlblätter weiter verfahren bis die Fleischmasse alle ist.

Nun die restlichen Zwiebeln und Knoblauch in Scheiben schneiden und mit etwas Öl in einem Bräter scharf anbraten.
Die Kohlrouladen hineinlegen, mit Apfelsaft und Gemüsebrühe ablöschen, Lorbeerblätter hinzugeben, nochmal nachwürzen und nochmal kurz aufkochen lassen.

[url]http://www.macrovis-web.de/wp-content/uploads/2014/10/2014-10-26-13.08.29.jpg[/url]

Dann bei 45min und 200° (keine Umluft) im Backofen garen lassen.
Zu guter letzt die Kohlrouladen und Lorbeerblätter aus dem Bräter nehmen, die restlichen 100ml Schlagsahne hinzugeben und mit einem Mixstab alles pürieren, ggf. nachwürzen.

[url]http://www.macrovis-web.de/wp-content/uploads/2014/10/2014-10-26-14.12.02.jpg[/url]

Dazu passen ganz gut Salzkartoffeln mit Petersilie.

[url]http://www.macrovis-web.de/wp-content/uploads/2014/10/2014-10-26-14.16.41.jpg[/url]

[url]http://www.macrovis-web.de/wp-content/uploads/2014/10/2014-10-26-14.17.23.jpg[/url]
[/b][/quote]
Ich liebe Kohlrouladen!]]></content>
      <title></title>
    </message><avatar id="59224"><![CDATA[./avatare/german.gif]]></avatar><icon id="2"><![CDATA[./img/icons/thumbsup.gif]]></icon><in-thread id="213115"><![CDATA[Krieg der Töpfe CIII - Herbstgemüse]]></in-thread><in-board id="14" /></post><post id="1245641335"><user id="1198856" group-id="3"><![CDATA[seak`]]></user><date timestamp="1414344677">26.10.2014 18:31:17</date><message>
      <edited count="0"></edited>
      <content><![CDATA[[quote=213115,1245641187,"SpassCola"][b]
[i]Ey, ihr Fotzen, Herbstgerichte, Scheiße![/i]
[url]http://abload.de/img/bildschirmfoto2014-10hlqsf.jpg[/url]

[b]Kohlrouladen[/b]

[b]Zutatenliste[/b]
[list]
[*]1 Weißkohl
[*]80g Apfelringe
[*]1 Bund Petersilie
[*]1 El Fenchelsaat
[*]1 El Kümmel, ganz
[*]3 Zwiebeln
[*]500g Hackfleisch, gemischt
[*]2 Eier
[*]4 El Semmelbrösel
[*]200ml Schlagsahne
[*]200ml Apfelsaft
[*]300ml Gemüsebrühe
[*]2 Knoblauchzehen
[*]4 Lorbeerblätter
[*]Öl
[*]n.B. Salz &amp; Pfeffer
[/list]

[url]http://www.macrovis-web.de/wp-content/uploads/2014/10/2014-10-26-11.36.34.jpg[/url]

In einem großen Topf Wasser zum Kochen bringen. Aus dem Weißkohl den Strunk herausschneiden und mit einer Bratengabel oder Rouladenstäben hineinstechen.

[url]http://www.macrovis-web.de/wp-content/uploads/2014/10/2014-10-26-12.14.17.jpg[/url]

Den Weißkohl jetzt ins Wasser legen und ca. alle 2min lassen sich die äußeren Kohlblätter lösen.
Dann alle Blätter nochmal 5min im Wasser kochen lassen, abtropfen lassen und den dicken Stamm abschneiden.

[url]http://www.macrovis-web.de/wp-content/uploads/2014/10/2014-10-26-12.49.49.jpg[/url]

Apfelringe fein hacken und mit gehackter Petersilie in eine Schüssel geben.

Fenchelsaat und Kümmel in einer Pfanne ohne Öl erhitzen bis die angebräunt sind, dann im Mörser oder mit Mixstab fein zerkleinern, mit in die Schüssel geben.
In der Pfanne dann mit wenig Öl eine fein gehackte Zwiebel glasig braten und auch mit in die Schüssel geben.

In die Schüssel kommen jetzt noch Hack, die Eier, Semmelbrösel und 100ml Schlagsahne.
Ordentlich mit Salz und Pfeffer würzen und gut durchmischen.

[url]http://www.macrovis-web.de/wp-content/uploads/2014/10/2014-10-26-12.04.14.jpg[/url]

Jetzt jeweils 2 Kohlblätter überlappt übereinander legen, eventuell mit Nudelholz anpressen, und ein wenig Hackmasse darauf legen.
Die Kohlblattkanten übereinander legen und dann die Roulade rollen, auf der Naht hinlegen.

[url]http://www.macrovis-web.de/wp-content/uploads/2014/10/2014-10-26-12.52.55.jpg[/url]

Mit allen Kohlblätter weiter verfahren bis die Fleischmasse alle ist.

Nun die restlichen Zwiebeln und Knoblauch in Scheiben schneiden und mit etwas Öl in einem Bräter scharf anbraten.
Die Kohlrouladen hineinlegen, mit Apfelsaft und Gemüsebrühe ablöschen, Lorbeerblätter hinzugeben, nochmal nachwürzen und nochmal kurz aufkochen lassen.

[url]http://www.macrovis-web.de/wp-content/uploads/2014/10/2014-10-26-13.08.29.jpg[/url]

Dann bei 45min und 200° (keine Umluft) im Backofen garen lassen.
Zu guter letzt die Kohlrouladen und Lorbeerblätter aus dem Bräter nehmen, die restlichen 100ml Schlagsahne hinzugeben und mit einem Mixstab alles pürieren, ggf. nachwürzen.

[url]http://www.macrovis-web.de/wp-content/uploads/2014/10/2014-10-26-14.12.02.jpg[/url]

Dazu passen ganz gut Salzkartoffeln mit Petersilie.

[url]http://www.macrovis-web.de/wp-content/uploads/2014/10/2014-10-26-14.16.41.jpg[/url]

[url]http://www.macrovis-web.de/wp-content/uploads/2014/10/2014-10-26-14.17.23.jpg[/url]
[/b][/quote]

Fick ja!]]></content>
      <title></title>
    </message><avatar id="60871"><![CDATA[./avatare/upload/U1198856--seak_bender.png]]></avatar><in-thread id="213115"><![CDATA[Krieg der Töpfe CIII - Herbstgemüse]]></in-thread><in-board id="14" /></post><post id="1245642839"><user id="3773" group-id="3"><![CDATA[[DtS]Scarface]]></user><date timestamp="1414429099">27.10.2014 17:58:19</date><message>
      <edited count="0"></edited>
      <content><![CDATA[Das wird schwer zu toppen! ^^]]></content>
      <title></title>
    </message><avatar id="60289"><![CDATA[./avatare/upload/U3773--scarface2.gif]]></avatar><icon id="2"><![CDATA[./img/icons/thumbsup.gif]]></icon><in-thread id="213115"><![CDATA[Krieg der Töpfe CIII - Herbstgemüse]]></in-thread><in-board id="14" /></post><post id="1245645271"><user id="1296761" group-id="3"><![CDATA[dictyosom]]></user><date timestamp="1414547994">29.10.2014 02:59:54</date><message>
      <edited count="0"></edited>
      <content><![CDATA[Es ist Herbst, macht was mit Pilzen, ihr Ficker! :o]]></content>
      <title></title>
    </message><avatar id="60920"><![CDATA[./avatare/upload/U1296761--ceras_s2okjfs.png]]></avatar><in-thread id="213115"><![CDATA[Krieg der Töpfe CIII - Herbstgemüse]]></in-thread><in-board id="14" /></post><post id="1245646310"><user id="59038" group-id="3"><![CDATA[Kebap]]></user><date timestamp="1414604306">29.10.2014 18:38:26</date><message>
      <edited count="2"><lastedit>
        <user id="59038"><![CDATA[Kebap]]></user>
        <date timestamp="1414604455">29.10.2014 18:40:55</date>
      </lastedit></edited>
      <content><![CDATA[Kohlrouladen lässt man für DEN Geschmack 1 Tag ziehen nach dem anbraten.


Guten Tag. :|

E. und diese ganzen mumu Zutaten ala Apfel, Fenchel und haste nich gesehen habe nichts in Kohlrouladen verloren! :mad:]]></content>
      <title></title>
    </message><avatar id="59549"><![CDATA[./avatare/kebap.gif]]></avatar><in-thread id="213115"><![CDATA[Krieg der Töpfe CIII - Herbstgemüse]]></in-thread><in-board id="14" /></post></posts></thread>